OrdinaryGacha/OrdinaryGacha.py
OrdinaryGacha/__init__.py
OrdinaryGacha-0.0.3.dist-info/LICENSE.txt
OrdinaryGacha-0.0.3.dist-info/METADATA
OrdinaryGacha-0.0.3.dist-info/WHEEL
OrdinaryGacha-0.0.3.dist-info/top_level.txt
OrdinaryGacha-0.0.3.dist-info/RECORD
