Metadata-Version: 2.1
Name: OrdinaryGacha
Version: 0.0.3
Summary: OrdinaryGacha เป็นแพ็กเกจสำหรับช่วยในการทำระบบสุ่มกาชาธรรมดา
Author-email: NatchaLatte Official <foxteary@gmail.com>
Project-URL: Homepage, https://github.com/NatchaLatte/OrdinaryGacha
Project-URL: Issues, https://github.com/NatchaLatte/OrdinaryGacha/issues
Classifier: Programming Language :: Python :: 3
Classifier: License :: OSI Approved :: MIT License
Classifier: Operating System :: OS Independent
Requires-Python: >=3.8
License-File: LICENSE.txt
